mixedbread/__init__.py
mixedbread/_base_client.py
mixedbread/_client.py
mixedbread/_compat.py
mixedbread/_constants.py
mixedbread/_exceptions.py
mixedbread/_files.py
mixedbread/_models.py
mixedbread/_qs.py
mixedbread/_resource.py
mixedbread/_response.py
mixedbread/_streaming.py
mixedbread/_types.py
mixedbread/_version.py
mixedbread/pagination.py
mixedbread/py.typed
mixedbread/_utils/__init__.py
mixedbread/_utils/_compat.py
mixedbread/_utils/_datetime_parse.py
mixedbread/_utils/_logs.py
mixedbread/_utils/_proxy.py
mixedbread/_utils/_reflection.py
mixedbread/_utils/_resources_proxy.py
mixedbread/_utils/_streams.py
mixedbread/_utils/_sync.py
mixedbread/_utils/_transform.py
mixedbread/_utils/_typing.py
mixedbread/_utils/_utils.py
mixedbread/lib/.keep
mixedbread/lib/polling.py
mixedbread/resources/__init__.py
mixedbread/resources/api_keys.py
mixedbread/resources/chat.py
mixedbread/resources/embeddings.py
mixedbread/resources/files.py
mixedbread/resources/data_sources/__init__.py
mixedbread/resources/data_sources/connectors.py
mixedbread/resources/data_sources/data_sources.py
mixedbread/resources/extractions/__init__.py
mixedbread/resources/extractions/content.py
mixedbread/resources/extractions/extractions.py
mixedbread/resources/extractions/jobs.py
mixedbread/resources/extractions/schema.py
mixedbread/resources/parsing/__init__.py
mixedbread/resources/parsing/jobs.py
mixedbread/resources/parsing/parsing.py
mixedbread/resources/stores/__init__.py
mixedbread/resources/stores/files.py
mixedbread/resources/stores/stores.py
mixedbread/resources/vector_stores/__init__.py
mixedbread/resources/vector_stores/files.py
mixedbread/resources/vector_stores/vector_stores.py
mixedbread/types/__init__.py
mixedbread/types/api_key.py
mixedbread/types/api_key_create_params.py
mixedbread/types/api_key_created.py
mixedbread/types/api_key_delete_response.py
mixedbread/types/api_key_list_params.py
mixedbread/types/client_embed_params.py
mixedbread/types/client_rerank_params.py
mixedbread-0.45.0.dist-info/METADATA
mixedbread-0.45.0.dist-info/WHEEL
mixedbread-0.45.0.dist-info/licenses/LICENSE
mixedbread-0.45.0.dist-info/RECORD
